cprex/__init__.py
cprex/commands.py
cprex/corpus/__init__.py
cprex/corpus/corpus.py
cprex/crawler/__init__.py
cprex/crawler/chemrxiv.py
cprex/ner/__init__.py
cprex/ner/abbreviations.py
cprex/ner/chem_ner.py
cprex/ner/properties.py
cprex/ner/quantities.py
cprex/parser/__init__.py
cprex/parser/pdf_parser.py
cprex/pipeline.py
cprex/rel/__init__.py
cprex/rel/configs/rel_tok2vec.cfg
cprex/rel/configs/rel_trf.cfg
cprex/rel/custom_functions.py
cprex/rel/evaluate.py
cprex/rel/parse_data.py
cprex/rel/rel_model.py
cprex/rel/rel_pipe.py
cprex-0.3.0.dist-info/LICENSE
cprex-0.3.0.dist-info/METADATA
cprex-0.3.0.dist-info/WHEEL
cprex-0.3.0.dist-info/entry_points.txt
cprex-0.3.0.dist-info/RECORD
