Metadata-Version: 2.1
Name: cprex
Version: 0.3.0
Summary: Chemical Properties Relation Extraction
Home-page: https://github.com/jonasrenault/cprex#readme
License: MIT
Keywords: pubchem,crawler,chemistry,machine-learning,relation-extraction,named-entity-extraction,deep-learning,transformers,spacy,scientific-articles
Author: Jonas Renault
Author-email: jonasrenault@gmail.com
Requires-Python: >=3.11,<4.0
Classifier: License :: OSI Approved :: MIT License
Classifier: Programming Language :: Python :: 3
Classifier: Programming Language :: Python :: 3.11
Classifier: Programming Language :: Python :: 3.12
Requires-Dist: beautifulsoup4 (>=4.12.3,<5.0.0)
Requires-Dist: click (>=8.1.7,<9.0.0)
Requires-Dist: grobid-quantities-client (>=0.4.0,<0.5.0)
Requires-Dist: lxml (>=5.1.0,<6.0.0)
Requires-Dist: pandas (>=2.2.1,<3.0.0)
Requires-Dist: ratelimit (>=2.2.1,<3.0.0)
Requires-Dist: requests (>=2.31.0,<3.0.0)
Requires-Dist: scikit-learn (>=1.4.1.post1,<2.0.0)
Requires-Dist: spacy (>=3.7.4,<4.0.0)
Requires-Dist: spacy-transformers (>=1.3.4,<2.0.0)
Requires-Dist: torch (>=2.2.1,<3.0.0)
Requires-Dist: tqdm (>=4.66.2,<5.0.0)
Requires-Dist: transformers (>=3.4.0,<4.37.0)
Project-URL: Repository, https://github.com/jonasrenault/cprex
